CMakeLists.txt
LICENSE
MANIFEST.in
NOTICE
README.md
setup.cfg
3rdparty/cub/cub/cub.cuh
3rdparty/cub/cub/util_allocator.cuh
3rdparty/cub/cub/util_arch.cuh
3rdparty/cub/cub/util_debug.cuh
3rdparty/cub/cub/util_device.cuh
3rdparty/cub/cub/util_macro.cuh
3rdparty/cub/cub/util_namespace.cuh
3rdparty/cub/cub/util_ptx.cuh
3rdparty/cub/cub/util_type.cuh
3rdparty/cub/cub/agent/agent_histogram.cuh
3rdparty/cub/cub/agent/agent_radix_sort_downsweep.cuh
3rdparty/cub/cub/agent/agent_radix_sort_upsweep.cuh
3rdparty/cub/cub/agent/agent_reduce.cuh
3rdparty/cub/cub/agent/agent_reduce_by_key.cuh
3rdparty/cub/cub/agent/agent_rle.cuh
3rdparty/cub/cub/agent/agent_scan.cuh
3rdparty/cub/cub/agent/agent_segment_fixup.cuh
3rdparty/cub/cub/agent/agent_select_if.cuh
3rdparty/cub/cub/agent/agent_spmv_orig.cuh
3rdparty/cub/cub/agent/single_pass_scan_operators.cuh
3rdparty/cub/cub/block/block_adjacent_difference.cuh
3rdparty/cub/cub/block/block_discontinuity.cuh
3rdparty/cub/cub/block/block_exchange.cuh
3rdparty/cub/cub/block/block_histogram.cuh
3rdparty/cub/cub/block/block_load.cuh
3rdparty/cub/cub/block/block_radix_rank.cuh
3rdparty/cub/cub/block/block_radix_sort.cuh
3rdparty/cub/cub/block/block_raking_layout.cuh
3rdparty/cub/cub/block/block_reduce.cuh
3rdparty/cub/cub/block/block_scan.cuh
3rdparty/cub/cub/block/block_shuffle.cuh
3rdparty/cub/cub/block/block_store.cuh
3rdparty/cub/cub/block/specializations/block_histogram_atomic.cuh
3rdparty/cub/cub/block/specializations/block_histogram_sort.cuh
3rdparty/cub/cub/block/specializations/block_reduce_raking.cuh
3rdparty/cub/cub/block/specializations/block_reduce_raking_commutative_only.cuh
3rdparty/cub/cub/block/specializations/block_reduce_warp_reductions.cuh
3rdparty/cub/cub/block/specializations/block_scan_raking.cuh
3rdparty/cub/cub/block/specializations/block_scan_warp_scans.cuh
3rdparty/cub/cub/block/specializations/block_scan_warp_scans2.cuh
3rdparty/cub/cub/block/specializations/block_scan_warp_scans3.cuh
lightseq.egg-info/PKG-INFO
lightseq.egg-info/SOURCES.txt
lightseq.egg-info/dependency_links.txt
lightseq.egg-info/entry_points.txt
lightseq.egg-info/not-zip-safe
lightseq.egg-info/requires.txt
lightseq.egg-info/top_level.txt
lightseq-3.0.1.dist-info/LICENSE
lightseq-3.0.1.dist-info/METADATA
lightseq-3.0.1.dist-info/NOTICE
lightseq-3.0.1.dist-info/WHEEL
lightseq-3.0.1.dist-info/entry_points.txt
lightseq-3.0.1.dist-info/top_level.txt
lightseq-3.0.1.dist-info/RECORD
