Metadata-Version: 2.1
Name: lightseq
Version: 3.0.1
Summary: LightSeq is a high performance library for sequence processing and generation
Home-page: https://github.com/bytedance/lightseq
Author: Xiaohui Wang, Ying Xiong, Xian Qian, Yang Wei
Author-email: wangxiaohui.neo@bytedance.com, xiongying.taka@bytedance.com, qian.xian@bytedance.com, weiyang.god@bytedance.com
License: UNKNOWN
Platform: UNKNOWN
Classifier: Programming Language :: Python :: 3
Classifier: License :: OSI Approved :: Apache Software License
Classifier: Operating System :: POSIX :: Linux
Requires-Python: >=3.6
License-File: LICENSE
License-File: NOTICE
Requires-Dist: ninja
Requires-Dist: numpy
Requires-Dist: scipy
